mesa_SIR/SIR.py
mesa_SIR/__init__.py
mesa_SIR/calculations_and_plots.py
mesa_SIR-0.0.3.dist-info/LICENSE.txt
mesa_SIR-0.0.3.dist-info/METADATA
mesa_SIR-0.0.3.dist-info/WHEEL
mesa_SIR-0.0.3.dist-info/top_level.txt
mesa_SIR-0.0.3.dist-info/RECORD
