Metadata-Version: 2.1
Name: mesa-SIR
Version: 0.0.3
Summary: A Mesa extension for SIR models
Home-page: https://github.com/metalcorebear/COVID-Agent-Based-Model
Author: Mark Bailey and Tom Pike
Author-email: mark.mbailey@gmail.com
License: UNKNOWN
Platform: UNKNOWN
Classifier: Topic :: Scientific/Engineering
Classifier: Topic :: Scientific/Engineering :: Artificial Life
Classifier: Topic :: Scientific/Engineering :: Artificial Intelligence
Classifier: Intended Audience :: Science/Research
Classifier: Programming Language :: Python :: 3 :: Only
Classifier: License :: OSI Approved :: MIT License
Classifier: Operating System :: OS Independent
Classifier: Development Status :: 2 - Pre-Alpha
Classifier: Natural Language :: English
Requires-Python: >=3.6
